<?xml version="1.0" encoding="utf-8"?>
<!DOCTYPE hibernate-mapping PUBLIC "-//Hibernate/Hibernate Mapping DTD 3.0//EN"
        "http://hibernate.sourceforge.net/hibernate-mapping-3.0.dtd">
<!-- 
    Mapping file autogenerated by MyEclipse Persistence Tools
-->
<hibernate-mapping>
    <class name="com.wuye.entity.RoomPartyRel" table="room_party_rel">
        <id name="roomPartyRelId" type="java.lang.Integer">
            <column name="room_party_rel_id"/>
            <generator class="native"/>
        </id>
        <many-to-one name="partyInfo" class="com.wuye.entity.PartyInfo" fetch="select">
            <column name="party_info_id"/>
        </many-to-one>
        <many-to-one name="room" class="com.wuye.entity.Room" fetch="select">
            <column name="room_id"/>
        </many-to-one>
        <property name="relType" type="java.lang.String">
            <column name="rel_type" length="2">
                <comment>10：业主，11：其它</comment>
            </column>
        </property>
        <property name="remark" type="java.lang.String">
            <column name="remark" length="200"/>
        </property>
        <property name="createDate" type="java.sql.Timestamp">
            <column name="create_date" length="19"/>
        </property>
        <property name="updateDate" type="java.sql.Timestamp">
            <column name="update_date" length="19"/>
        </property>
        <property name="statusCd" type="java.lang.String">
            <column name="status_cd" length="4"/>
        </property>
        <property name="statusDate" type="java.sql.Timestamp">
            <column name="status_date" length="19"/>
        </property>
    </class>
</hibernate-mapping>
